{"_ts":[1575168011],"_r":{"breakdown":{"html":{"bytes":[25627],"requests":[4]},"js":{"bytes":[520749],"requests":[17]},"css":{"bytes":[24863],"requests":[3]},"image":{"bytes":[5583987],"requests":[45]},"flash":{"bytes":[0],"requests":[0]},"font":{"bytes":[218223],"requests":[4]},"video":{"bytes":[0],"requests":[0]},"other":{"bytes":[15631],"requests":[8]}},"date":[1575168011],"domElements":[1059],"domInteractive":[1215],"firstPaint":[815.36749999945],"fullyLoaded":[12412.5],"id":["191201_S1_833478a2bbd7f17bb78dc62177fbafef"],"loadTime":[11457],"render":[1250],"SpeedIndex":[1468.5],"TTFB":[498],"videoFrames":[[{"_i":"ms_000000.jpg","_t":0,"_vc":0},{"_i":"ms_001300.jpg","_t":1300,"_vc":68},{"_i":"ms_001500.jpg","_t":1500,"_vc":77},{"_i":"ms_001600.jpg","_t":1600,"_vc":78},{"_i":"ms_001800.jpg","_t":1800,"_vc":84},{"_i":"ms_001900.jpg","_t":1900,"_vc":84},{"_i":"ms_002000.jpg","_t":2000,"_vc":84},{"_i":"ms_002500.jpg","_t":2500,"_vc":100}]],"visualComplete":[2400],"lighthouse":[31],"pagespeed":[null]}}